techlens_metrics/__init__.py
techlens_metrics/__main__.py
techlens_metrics/config.py
techlens_metrics/diff_process.py
techlens_metrics/fp.py
techlens_metrics/cls/__init__.py
techlens_metrics/cls/base.py
techlens_metrics/cls/base_calc.py
techlens_metrics/cls/base_stats.py
techlens_metrics/cls/modules.py
techlens_metrics/cls/calc/__init__.py
techlens_metrics/cls/calc/halstead.py
techlens_metrics/cls/calc/maintenance.py
techlens_metrics/cls/calc/pylint.py
techlens_metrics/cls/calc/tiobe.py
techlens_metrics/cls/importer/__init__.py
techlens_metrics/cls/importer/base.py
techlens_metrics/cls/importer/filtered.py
techlens_metrics/cls/importer/pick.py
techlens_metrics/cls/importer/mods/__init__.py
techlens_metrics/cls/importer/mods/csv.py
techlens_metrics/cls/importer/mods/json.py
techlens_metrics/cls/metric/__init__.py
techlens_metrics/cls/metric/comments.py
techlens_metrics/cls/metric/cyclomatic.py
techlens_metrics/cls/metric/fanout.py
techlens_metrics/cls/metric/loc.py
techlens_metrics/cls/metric/operands.py
techlens_metrics/cls/metric/operators.py
techlens_metrics/cls/stats/__init__.py
techlens_metrics/cls/stats/stats.py
techlens_metrics-0.3.0.dist-info/METADATA
techlens_metrics-0.3.0.dist-info/WHEEL
techlens_metrics-0.3.0.dist-info/licenses/LICENSE
techlens_metrics-0.3.0.dist-info/RECORD
