Metadata-Version: 2.4
Name: techlens-metrics
Version: 0.3.0
Summary: Calculate code metrics in various languages
Project-URL: Homepage, https://www.crosslaketech.com/
Author-email: Crosslake Technologies <techlens@crosslaketech.com>
License-Expression: CC-BY-NC-4.0
License-File: LICENSE
Classifier: Environment :: Console
Classifier: Intended Audience :: Developers
Classifier: License :: Free for non-commercial use
Classifier: Natural Language :: English
Classifier: Programming Language :: Python :: 3
Requires-Python: >=3.10
Requires-Dist: chardet>=5.2.0
Requires-Dist: httpx[http2]~=0.28.1
Requires-Dist: pygments==2.19.2
Requires-Dist: pygount
Requires-Dist: techlens-cache-utils==0.2.0
Requires-Dist: techlens-pygments-tsx==0.3.0
Provides-Extra: dev
Requires-Dist: black>=24.1.1; extra == 'dev'
Requires-Dist: pytest; extra == 'dev'
Requires-Dist: pytest-cov; extra == 'dev'
